{
  "openingId": "alekhine-defense-modern-variation-alekhine-gambit",
  "moveAnnotations": [
    {
      "san": "e4",
      "annotation": "We're opening with the most classical and direct first move in chess, staking an immediate claim to the center and freeing both our bishop and queen for future development. This move controls the crucial d5 and f5 squares while opening lines for our pieces to enter the game. The move 1.e4 leads to sharp, tactical games where both sides fight for the initiative from the very beginning. Our plan is to build a strong pawn center and develop our pieces quickly to put pressure on Black's position.",
      "arrows": [
        {
          "from": "e2",
          "to": "e4",
          "color": "rgba(0, 180, 80, 0.8)"
        }
      ],
      "highlights": [
        {
          "square": "e4",
          "color": "rgba(255, 255, 0, 0.4)"
        }
      ]
    },
    {
      "san": "Nf6",
      "annotation": "Black responds with the provocative Alekhine Defense, immediately attacking our central pawn and inviting us to advance it further up the board. This hypermodern approach says 'go ahead and build your pawn center - I'll attack it later when it becomes overextended.' The knight on f6 also prepares to retreat to various squares like d7, h5, or d5 depending on how we continue. While this defense can lead to sharp positions, it requires precise play from Black since the early knight moves can lose tempo if not handled carefully.",
      "arrows": [
        {
          "from": "g8",
          "to": "f6",
          "color": "rgba(0, 180, 80, 0.8)"
        }
      ],
      "highlights": [
        {
          "square": "f6",
          "color": "rgba(255, 255, 0, 0.4)"
        }
      ]
    },
    {
      "san": "e5",
      "annotation": "We're accepting Black's challenge by advancing our pawn and attacking the knight, gaining space in the center and forcing Black's pieces to move again. This advance gives us a strong foothold on e5 and restricts Black's pieces, particularly limiting the scope of the f6 knight. The pawn on e5 also supports a future d4 advance, which would give us a classical pawn center. However, we must be aware that this advanced pawn could become a target later in the game if we're not careful with our piece coordination.",
      "arrows": [
        {
          "from": "e4",
          "to": "e5",
          "color": "rgba(0, 180, 80, 0.8)"
        }
      ],
      "highlights": [
        {
          "square": "e5",
          "color": "rgba(255, 255, 0, 0.4)"
        }
      ]
    },
    {
      "san": "Nd5",
      "annotation": "Black's knight retreats to the excellent central square d5, where it cannot be immediately attacked by our pawns and exerts influence over important squares like c3, e3, f4, and b4. From d5, the knight is well-placed and forces us to make a decision about how to handle this centralized piece. This retreat is much better than going to h5 or d7, as the knight stays active and challenges our central control. Black is following the Alekhine Defense philosophy of allowing us to build our center while preparing to undermine it later.",
      "arrows": [
        {
          "from": "f6",
          "to": "d5",
          "color": "rgba(0, 180, 80, 0.8)"
        }
      ],
      "highlights": [
        {
          "square": "d5",
          "color": "rgba(255, 255, 0, 0.4)"
        }
      ]
    },
    {
      "san": "d4",
      "annotation": "We're establishing our ideal pawn center with this advance, creating a strong pawn duo on d4 and e5 that controls key central squares and gives us significant space advantage. The d4 pawn attacks Black's knight on d5, forcing it to move again and gaining us another tempo in development. This classical center formation supports our pieces and makes it difficult for Black to find comfortable squares for development. Our next moves will focus on piece development while maintaining this central advantage and preventing Black from effectively challenging our pawn structure.",
      "arrows": [
        {
          "from": "d2",
          "to": "d4",
          "color": "rgba(0, 180, 80, 0.8)"
        }
      ],
      "highlights": [
        {
          "square": "d4",
          "color": "rgba(255, 255, 0, 0.4)"
        }
      ]
    },
    {
      "san": "d6",
      "annotation": "Black immediately challenges our advanced e5 pawn, striking at the base of our pawn center and preparing to potentially exchange it off the board. This move also opens the diagonal for Black's light-squared bishop and prepares moves like ...dxe5, which would eliminate our advanced pawn. By attacking e5, Black is implementing the key strategic idea of the Alekhine Defense: allow White to build the center, then systematically attack and undermine it. We need to be prepared to either defend our e5 pawn or consider whether advancing to e6 might be appropriate in some lines.",
      "arrows": [
        {
          "from": "d7",
          "to": "d6",
          "color": "rgba(0, 180, 80, 0.8)"
        }
      ],
      "highlights": [
        {
          "square": "d6",
          "color": "rgba(255, 255, 0, 0.4)"
        }
      ]
    },
    {
      "san": "c4",
      "annotation": "We're driving away the centralized knight with this advance, while simultaneously expanding our control over the center and queenside. The c4 pawn attacks the knight on d5 and also controls the important d5 and b5 squares, further restricting Black's piece placement. This move fits perfectly with our opening strategy of gaining space and forcing Black's pieces to less active squares. Additionally, c4 prepares the development of our queenside pieces and gives us more options for piece coordination, though we must be mindful that this pawn could also become a target if Black can organize counterplay.",
      "arrows": [
        {
          "from": "c2",
          "to": "c4",
          "color": "rgba(0, 180, 80, 0.8)"
        }
      ],
      "highlights": [
        {
          "square": "c4",
          "color": "rgba(255, 255, 0, 0.4)"
        }
      ]
    },
    {
      "san": "Nb6",
      "annotation": "Black's knight retreats to b6, where it's temporarily safe but somewhat out of play on the rim of the board. From b6, the knight eyes the c4 pawn and potentially prepares to reroute via d7 or a4, though these squares aren't immediately available. This retreat demonstrates one of the drawbacks of the Alekhine Defense - Black's knight has been pushed around and is now on a less active square. However, the knight on b6 does attack our c4 pawn and could potentially support future pawn breaks like ...c5, so we shouldn't completely ignore its presence.",
      "arrows": [
        {
          "from": "d5",
          "to": "b6",
          "color": "rgba(0, 180, 80, 0.8)"
        }
      ],
      "highlights": [
        {
          "square": "b6",
          "color": "rgba(255, 255, 0, 0.4)"
        }
      ]
    },
    {
      "san": "Nf3",
      "annotation": "We're developing our kingside knight to its most natural square, where it controls important central squares like e5 (supporting our advanced pawn) and d4, while also preparing kingside castling. The knight on f3 is beautifully placed, supporting our pawn center and ready to participate in both attack and defense. This move also prepares the development of our light-squared bishop and brings us closer to castling safety. From f3, our knight can potentially jump to more aggressive squares like g5 or e5 if the tactical situation allows, making it a flexible and powerful piece in our position.",
      "arrows": [
        {
          "from": "g1",
          "to": "f3",
          "color": "rgba(0, 180, 80, 0.8)"
        }
      ],
      "highlights": [
        {
          "square": "f3",
          "color": "rgba(255, 255, 0, 0.4)"
        }
      ]
    },
    {
      "san": "Bg4",
      "annotation": "Black develops the bishop to an active square where it pins our knight to the queen, creating immediate tactical pressure and forcing us to deal with this pin before we can comfortably continue our development. This move also challenges our control of the center by attacking the knight that supports our d4 and e5 pawns. The bishop on g4 is actively placed and fits well with Black's strategy of creating counterplay against our central pawn structure. However, the bishop could become a target itself, and we have several ways to address this pin, including Be2, h3, or even accepting the pin for now while continuing development.",
      "arrows": [
        {
          "from": "c8",
          "to": "g4",
          "color": "rgba(0, 180, 80, 0.8)"
        }
      ],
      "highlights": [
        {
          "square": "g4",
          "color": "rgba(255, 255, 0, 0.4)"
        }
      ]
    },
    {
      "san": "Be2",
      "annotation": "We're breaking the annoying pin by developing our light-squared bishop to e2, where it supports the pinned knight and prepares kingside castling. This quiet but solid move resolves the tactical problem of the pin while keeping our pieces well-coordinated and maintaining our central advantage. The bishop on e2 also eyes the long diagonal toward h5 and could potentially support future attacking ideas on the kingside. While this move might seem passive, it's actually quite practical - we maintain our strong center, solve our immediate tactical concerns, and prepare to complete our kingside development with castling, after which we can consider more aggressive plans.",
      "arrows": [
        {
          "from": "f1",
          "to": "e2",
          "color": "rgba(0, 180, 80, 0.8)"
        }
      ],
      "highlights": [
        {
          "square": "e2",
          "color": "rgba(255, 255, 0, 0.4)"
        }
      ]
    }
  ]
}