{
  "openingId": "queens-gambit-accepted-classical-furman-variation",
  "moveAnnotations": [
    {
      "san": "d4",
      "annotation": "We're opening with the queen's pawn, staking our claim to the center and preparing to support it with pieces. This move controls the important e5 and c5 squares while opening lines for our queen and dark-squared bishop. The d4 opening leads to more positional, strategic games compared to 1.e4, where we'll focus on solid piece development and gradual pressure rather than immediate tactics. Our plan is to build a strong pawn center and develop our pieces harmoniously to dominate the middlegame.",
      "arrows": [
        {
          "from": "d2",
          "to": "d4",
          "color": "rgba(0, 180, 80, 0.8)"
        }
      ],
      "highlights": [
        {
          "square": "d4",
          "color": "rgba(255, 255, 0, 0.4)"
        }
      ]
    },
    {
      "san": "d5",
      "annotation": "Black responds symmetrically in the center, immediately challenging our d4 pawn and fighting for central control. This is the most principled response, as it prevents us from simply advancing e2-e4 and claiming a massive pawn center. Our opponent is preparing to develop pieces while maintaining equality in the center, and this move opens up the c8-bishop's diagonal. Now we have several options, but the most popular and aggressive approach is to offer the Queen's Gambit with c2-c4.",
      "arrows": [
        {
          "from": "d7",
          "to": "d5",
          "color": "rgba(0, 180, 80, 0.8)"
        }
      ],
      "highlights": [
        {
          "square": "d5",
          "color": "rgba(255, 255, 0, 0.4)"
        }
      ]
    },
    {
      "san": "c4",
      "annotation": "We're offering the famous Queen's Gambit, attacking Black's central d5 pawn and trying to deflect it from the center. This isn't a true gambit since we can usually regain the pawn later, but it's a powerful way to fight for central control and open lines for our pieces. If Black takes on c4, we'll have given up a pawn temporarily but gained time and space to develop with tempo. The move also prepares Nc3 to support our d4 pawn and puts immediate pressure on Black's position.",
      "arrows": [
        {
          "from": "c2",
          "to": "c4",
          "color": "rgba(0, 180, 80, 0.8)"
        }
      ],
      "highlights": [
        {
          "square": "c4",
          "color": "rgba(255, 255, 0, 0.4)"
        }
      ]
    },
    {
      "san": "dxc4",
      "annotation": "Black accepts the Queen's Gambit, capturing our c4 pawn and temporarily winning material. This is a perfectly sound choice that leads to sharp, tactical play where Black tries to hold onto the extra pawn while we seek rapid development and central control. Our opponent is essentially saying 'I'll take your pawn and dare you to prove you have enough compensation.' Now we need to develop quickly and put pressure on Black's position before they can consolidate their material advantage.",
      "arrows": [
        {
          "from": "d5",
          "to": "c4",
          "color": "rgba(0, 180, 80, 0.8)"
        }
      ],
      "highlights": [
        {
          "square": "c4",
          "color": "rgba(255, 80, 80, 0.3)"
        }
      ]
    },
    {
      "san": "Nf3",
      "annotation": "We develop our knight to its most natural square, attacking the e5 square and preparing to support our central ambitions. This move is more flexible than the immediate 3.e3 because it doesn't commit our pawn structure yet and keeps more options open. Our knight from f3 can later jump to e5, g5, or support an eventual e4 advance, making it a key piece in our attacking setup. We're following the opening principle of developing pieces before moving pawns, while also preparing to recapture our gambit pawn.",
      "arrows": [
        {
          "from": "g1",
          "to": "f3",
          "color": "rgba(0, 180, 80, 0.8)"
        }
      ],
      "highlights": [
        {
          "square": "f3",
          "color": "rgba(255, 255, 0, 0.4)"
        }
      ]
    },
    {
      "san": "Nf6",
      "annotation": "Black develops their knight to an active square, mirroring our development and fighting for central control. This move attacks our e4 square, preventing us from immediately advancing our king's pawn, while also preparing to support the c4 pawn with moves like ...b5. Our opponent is developing sensibly and trying to consolidate their extra material by getting pieces out and controlling key squares. The knight on f6 also prepares castling and keeps Black's options open for various defensive setups.",
      "arrows": [
        {
          "from": "g8",
          "to": "f6",
          "color": "rgba(0, 180, 80, 0.8)"
        }
      ],
      "highlights": [
        {
          "square": "f6",
          "color": "rgba(255, 255, 0, 0.4)"
        }
      ]
    },
    {
      "san": "e3",
      "annotation": "We advance our king's pawn one square, supporting our d4 center and preparing to develop our dark-squared bishop to recapture the c4 pawn. This move is more solid than the immediate 4.e4, which would be too aggressive since Black could simply play ...e5, attacking our advanced pawns. Our e3 move creates a strong pawn triangle (d4-e3-f2) that provides excellent support for our pieces while preparing Bxc4. We're building our position methodically, prioritizing piece development and pawn recapture over immediate tactical shots.",
      "arrows": [
        {
          "from": "e2",
          "to": "e3",
          "color": "rgba(0, 180, 80, 0.8)"
        }
      ],
      "highlights": [
        {
          "square": "e3",
          "color": "rgba(255, 255, 0, 0.4)"
        }
      ]
    },
    {
      "san": "e6",
      "annotation": "Black plays the solid French Defense-style pawn move, supporting their knight on f6 and preparing to develop the light-squared bishop. This move creates a solid pawn chain and prevents any immediate tactics involving our pieces attacking the f6 knight. Our opponent is building a fortress-like position where they can slowly consolidate their extra pawn while keeping their king safe. However, this move also slightly restricts Black's light-squared bishop, which will need to find a good square later in the opening.",
      "arrows": [
        {
          "from": "e7",
          "to": "e6",
          "color": "rgba(0, 180, 80, 0.8)"
        }
      ],
      "highlights": [
        {
          "square": "e6",
          "color": "rgba(255, 255, 0, 0.4)"
        }
      ]
    },
    {
      "san": "Bxc4",
      "annotation": "We finally recapture our gambit pawn, developing our bishop to an active square where it aims at the f7 weakness and supports our central ambitions. This bishop placement is crucial in Queen's Gambit Accepted positions because it puts immediate pressure on Black's kingside and controls important central squares. Our bishop from c4 can later support pawn breaks like e4-e5 or participate in kingside attacks against the enemy king. Now we've regained material equality while maintaining a lead in development and piece activity.",
      "arrows": [
        {
          "from": "f1",
          "to": "c4",
          "color": "rgba(0, 180, 80, 0.8)"
        }
      ],
      "highlights": [
        {
          "square": "c4",
          "color": "rgba(255, 80, 80, 0.3)"
        }
      ]
    },
    {
      "san": "c5",
      "annotation": "Black strikes back in the center with this thematic pawn break, challenging our d4 pawn and trying to open lines for their pieces. This is the key liberating move in the Queen's Gambit Accepted, as it fights for space and attempts to activate Black's somewhat passive pieces. Our opponent is following the classical plan of counterattacking in the center rather than passively defending, which leads to sharp, tactical positions. This move also prepares to develop the light-squared bishop and gives Black chances for active piece play.",
      "arrows": [
        {
          "from": "c7",
          "to": "c5",
          "color": "rgba(0, 180, 80, 0.8)"
        }
      ],
      "highlights": [
        {
          "square": "c5",
          "color": "rgba(255, 255, 0, 0.4)"
        }
      ]
    },
    {
      "san": "Qe2",
      "annotation": "We develop our queen to a flexible square where it supports the e4 advance, connects our rooks, and maintains pressure on the position. This move is characteristic of the Furman Variation, where we're preparing a quick e4-e5 pawn storm while keeping our queen safely placed. Our queen from e2 can also swing to the kingside for attacking chances or support central pawn breaks depending on how the position develops. This is more flexible than placing the queen on other squares because it doesn't block any pieces and maintains maximum options.",
      "arrows": [
        {
          "from": "d1",
          "to": "e2",
          "color": "rgba(0, 180, 80, 0.8)"
        }
      ],
      "highlights": [
        {
          "square": "e2",
          "color": "rgba(255, 255, 0, 0.4)"
        }
      ]
    },
    {
      "san": "a6",
      "annotation": "Black plays this flexible move to control the b5 square and prevent any immediate Nb5 ideas from our side, while also preparing to expand with ...b5 if needed. This is a typical waiting move that doesn't commit to any particular pawn structure while improving Black's position slightly. Our opponent is also preparing to develop their pieces more actively and may be setting up the ...b5 advance to challenge our bishop on c4. The move fits into Black's general strategy of consolidating their position before committing to any major structural decisions.",
      "arrows": [
        {
          "from": "a7",
          "to": "a6",
          "color": "rgba(0, 180, 80, 0.8)"
        }
      ],
      "highlights": [
        {
          "square": "a6",
          "color": "rgba(255, 255, 0, 0.4)"
        }
      ]
    },
    {
      "san": "dxc5",
      "annotation": "We capture Black's c5 pawn, opening the center and eliminating a key defender of their position. This exchange simplifies the position in our favor because we maintain better piece development and can now target Black's somewhat loose pieces. Our decision to trade pawns also opens the d-file for our rooks and reduces Black's central presence, making it easier for us to launch a kingside attack. By eliminating the c5 pawn, we're also preparing to advance our e-pawn with greater effect since Black has fewer central pawns to block our advance.",
      "arrows": [
        {
          "from": "d4",
          "to": "c5",
          "color": "rgba(0, 180, 80, 0.8)"
        }
      ],
      "highlights": [
        {
          "square": "c5",
          "color": "rgba(255, 80, 80, 0.3)"
        }
      ]
    },
    {
      "san": "Bxc5",
      "annotation": "Black recaptures with the bishop, developing it to an active square where it controls important central squares and maintains material balance. This is the most natural recapture since it develops a piece while keeping the material even, and the bishop on c5 is well-placed to influence the center. Our opponent's bishop now eyes our e3 pawn and controls the long diagonal, which could become important in tactical sequences. However, this bishop placement also makes it a potential target for our future e4-e5 advance, which would attack it directly.",
      "arrows": [
        {
          "from": "f8",
          "to": "c5",
          "color": "rgba(0, 180, 80, 0.8)"
        }
      ],
      "highlights": [
        {
          "square": "c5",
          "color": "rgba(255, 80, 80, 0.3)"
        }
      ]
    },
    {
      "san": "O-O",
      "annotation": "We castle kingside to get our king to safety and connect our rooks, completing a crucial part of our development. This move is essential before launching any serious attacks, as it removes our king from the center where it could become a target. Our rook now moves to f1, where it can support the f7 square and participate in kingside operations or central pawn breaks. Castling also frees up our e1 square and allows us to consider more aggressive pawn advances like e4-e5 without worrying about king safety.",
      "arrows": [
        {
          "from": "e1",
          "to": "g1",
          "color": "rgba(0, 180, 80, 0.8)"
        }
      ],
      "highlights": [
        {
          "square": "g1",
          "color": "rgba(255, 255, 0, 0.4)"
        }
      ]
    },
    {
      "san": "Nc6",
      "annotation": "Black develops their knight to a natural square, increasing their control over the center and preparing to complete their development. This move supports the bishop on c5 and prepares potential pawn breaks or piece maneuvers in the center. Our opponent is following sound opening principles by developing pieces toward the center and maintaining flexibility in their pawn structure. The knight on c6 also prepares castling and keeps options open for various defensive setups, though it may become a target if we can advance e4-e5 with tempo.",
      "arrows": [
        {
          "from": "b8",
          "to": "c6",
          "color": "rgba(0, 180, 80, 0.8)"
        }
      ],
      "highlights": [
        {
          "square": "c6",
          "color": "rgba(255, 255, 0, 0.4)"
        }
      ]
    },
    {
      "san": "e4",
      "annotation": "We advance our central pawn, seizing more space in the center and preparing the powerful e4-e5 breakthrough that's characteristic of this variation. This move supports our pieces magnificently, giving our knights better central squares and preparing to drive back Black's pieces with tempo. Our pawn advance also opens up more space for our pieces to maneuver and creates threats against Black's somewhat cramped position. This is the key move that transforms our slight developmental advantage into concrete attacking chances.",
      "arrows": [
        {
          "from": "e3",
          "to": "e4",
          "color": "rgba(0, 180, 80, 0.8)"
        }
      ],
      "highlights": [
        {
          "square": "e4",
          "color": "rgba(255, 255, 0, 0.4)"
        }
      ]
    },
    {
      "san": "b5",
      "annotation": "Black strikes at our bishop and tries to gain space on the queenside, following the typical plan of counterplay in Queen's Gambit Accepted positions. This move challenges our active bishop and forces us to make a decision about where to retreat it, while also potentially preparing ...Bb7 to pressure our long diagonal. Our opponent is correctly seeking active counterplay rather than passively defending, though this pawn advance also weakens some light squares around Black's position. The move shows good understanding of the position's requirements, as Black needs active piece play to compensate for being slightly behind in development.",
      "arrows": [
        {
          "from": "b7",
          "to": "b5",
          "color": "rgba(0, 180, 80, 0.8)"
        }
      ],
      "highlights": [
        {
          "square": "b5",
          "color": "rgba(255, 255, 0, 0.4)"
        }
      ]
    },
    {
      "san": "e5",
      "annotation": "We unleash the powerful central pawn break that's the point of our entire opening setup, attacking Black's knight and seizing massive space in the center. This advance drives back the Nf6, our opponent's key defensive piece, while opening up tremendous attacking potential for our pieces. Our e5 pawn also controls key squares like d6 and f6, severely restricting Black's piece mobility and preparing various tactical threats. This is the culmination of our opening strategy, transforming our slight lead in development into concrete attacking chances and space advantage that will persist into the middlegame.",
      "arrows": [
        {
          "from": "e4",
          "to": "e5",
          "color": "rgba(0, 180, 80, 0.8)"
        }
      ],
      "highlights": [
        {
          "square": "e5",
          "color": "rgba(255, 255, 0, 0.4)"
        }
      ]
    }
  ]
}