{
  "openingId": "sicilian-defense-brick-variation",
  "moveAnnotations": [
    {
      "san": "e4",
      "annotation": "We're opening with the king's pawn advance, immediately claiming central space and freeing both our bishop on f1 and our queen for future development. This move controls the crucial d5 and f5 squares, preventing Black from easily establishing pieces there. The e4 pawn also supports a potential d4 advance later, which would give us a classical pawn center. This is one of the most principled first moves, leading to sharp, tactical games where both sides fight for the initiative from the very beginning.",
      "arrows": [
        {
          "from": "e2",
          "to": "e4",
          "color": "rgba(0, 180, 80, 0.8)"
        }
      ],
      "highlights": [
        {
          "square": "e4",
          "color": "rgba(255, 255, 0, 0.4)"
        }
      ]
    },
    {
      "san": "c5",
      "annotation": "Black responds with the Sicilian Defense, one of the most popular and combative responses to 1.e4. Rather than matching us in the center with 1...e5, our opponent strikes at our potential d4 square from the side, preventing us from easily establishing the ideal pawn center with d2-d4. The c5 pawn also prepares Black's queenside expansion and often supports a later ...d6 and ...Nf6 setup. This defense leads to unbalanced positions where Black often gets counterplay on the queenside while we typically attack on the kingside.",
      "arrows": [
        {
          "from": "c7",
          "to": "c5",
          "color": "rgba(0, 180, 80, 0.8)"
        }
      ],
      "highlights": [
        {
          "square": "c5",
          "color": "rgba(255, 255, 0, 0.4)"
        }
      ]
    },
    {
      "san": "Nh3",
      "annotation": "We're playing the highly unusual Brick Variation, developing our knight to the rim of the board where it's far less active than the normal Nf3. This offbeat move avoids the main theoretical lines of the Sicilian, potentially catching our opponent off-guard if they've prepared standard variations. However, from h3 our knight doesn't control the important central squares d4, e5, or f4, and it will likely need to be repositioned later via f4 or f2 to become more useful. While this move can lead to interesting and unexplored positions, it goes against the opening principle of developing pieces to their most active squares, making it more of a surprise weapon than a sound theoretical choice.",
      "arrows": [
        {
          "from": "g1",
          "to": "h3",
          "color": "rgba(0, 180, 80, 0.8)"
        }
      ],
      "highlights": [
        {
          "square": "h3",
          "color": "rgba(255, 255, 0, 0.4)"
        }
      ]
    }
  ]
}